mapidy/__init__.py
mapidy-0.0.1.dist-info/METADATA
mapidy-0.0.1.dist-info/WHEEL
mapidy-0.0.1.dist-info/top_level.txt
mapidy-0.0.1.dist-info/RECORD
