Metadata-Version: 2.4
Name: mapidy
Version: 0.0.1
Summary: Open-source toolkit to deploy projects from an architectural starting point.
Project-URL: Homepage, https://mapidy.com
Requires-Python: >=3.8
